grid_search_utils/__init__.py
grid_search_utils/plotting.py
grid_search_utils/tables.py
grid_search_utils/utils.py
tests/__init__.py
tests/test_plotting.py
tests/test_tables.py
tests/test_utils.py
grid_search_utils-0.1.dist-info/LICENSE
grid_search_utils-0.1.dist-info/METADATA
grid_search_utils-0.1.dist-info/WHEEL
grid_search_utils-0.1.dist-info/top_level.txt
grid_search_utils-0.1.dist-info/RECORD
