Metadata-Version: 2.1
Name: grid-search-utils
Version: 0.1
Summary: Utility functions for plotting and tabulating GridSearchCV results
Home-page: https://github.com/yourusername/grid_search_utils
Author: Diogo Hajjar
Author-email: your.email@example.com
Classifier: Programming Language :: Python :: 3.11
Classifier: License :: OSI Approved :: MIT License
Classifier: Operating System :: OS Independent
License-File: LICENSE
Requires-Dist: xgboost
Requires-Dist: scikit-learn
Requires-Dist: pandas
Requires-Dist: plotly
Requires-Dist: matplotlib
Requires-Dist: scipy
